src/register_file.v
/*
    Define 32 general-purpose registers
    Each register is 32 bits wide
*/

module register_file(
    input clk,                    // Clock
    input reset,                  // Reset signal
    input [4:0] rs1_addr,         // Source register 1 address
    input [4:0] rs2_addr,         // Source register 2 address
    input [4:0] rd_addr,          // Destination register address
    input [31:0] write_data,      // Data to write
    input reg_write,              // Register write enable
    output [31:0] rs1_data,       // Source register 1 data
    output [31:0] rs2_data        // Source register 2 data
);

    // List of all 32, 32-bit registers
    reg [31:0] registers [0:31];
        
    // Initialize all registers
    integer i;
    initial begin
        for (i = 0; i < 32; i = i + 1) begin
            registers[i] = 32'b0;
        end
    end

    // Define reset behavior
    always @(posedge clk) begin
        if (reset) begin
            for (i = 0; i < 32; i = i + 1) begin
                registers[i] <= 32'b0;
            end
        end
    end

    // Synchronous write behavior (avoid address x0)
    always @(posedge clk) begin
        if (reg_write && rd_addr != 5'b0) begin
            registers[rd_addr] <= write_data;
        end
    end

    //Asynchronous read behavior
    assign rs1_data = (rs1_addr == 5'b0) ? 32'b0 : registers[rs1_addr];
    assign rs2_data = (rs2_addr == 5'b0) ? 32'b0 : registers[rs2_addr];

endmodule

tb/register_block_tb.v
`timescale 1ns/1ps

module register_file_tb;
    // Inputs
    reg clk;
    reg reset;
    reg [4:0] rs1_addr;
    reg [4:0] rs2_addr;
    reg [4:0] rd_addr;
    reg [31:0] write_data;
    reg reg_write;
    
    // Outputs
    wire [31:0] rs1_data;
    wire [31:0] rs2_data;
    
    // Instantiate the register file
    register_file uut (
        .clk(clk),
        .reset(reset),
        .rs1_addr(rs1_addr),
        .rs2_addr(rs2_addr),
        .rd_addr(rd_addr),
        .write_data(write_data),
        .reg_write(reg_write),
        .rs1_data(rs1_data),
        .rs2_data(rs2_data)
    );
    
    // Clock generation
    always begin
        #5 clk = ~clk; // 10ns clock period
    end
    
    // Waveform generation
    initial begin
        $dumpfile("register_file_test.vcd");
        $dumpvars(0, register_file_tb);
    end
    
    // Test vector generator
    initial begin
        // Initialize signals
        clk = 0;
        reset = 1;
        rs1_addr = 0;
        rs2_addr = 0;
        rd_addr = 0;
        write_data = 0;
        reg_write = 0;
        
        // Apply reset
        #20;
        reset = 0;
        
        // Test 1: Write to register x1
        rd_addr = 5'd1;
        write_data = 32'hABCD1234;
        reg_write = 1;
        #10; // Wait for one clock cycle
        
        // Test 2: Read from register x1
        rs1_addr = 5'd1;
        reg_write = 0;
        #10;
        if (rs1_data !== 32'hABCD1234) 
            $display("Test 2 failed: Expected 0xABCD1234, got %h", rs1_data);
        else 
            $display("Test 2 passed");
        
        // Test 3: Write to register x2
        rd_addr = 5'd2;
        write_data = 32'h87654321;
        reg_write = 1;
        #10;
        
        // Test 4: Read from registers x1 and x2
        rs1_addr = 5'd1;
        rs2_addr = 5'd2;
        reg_write = 0;
        #10;
        if (rs1_data !== 32'hABCD1234 || rs2_data !== 32'h87654321)
            $display("Test 4 failed");
        else
            $display("Test 4 passed");
        
        // Test 5: Attempt to write to x0 (should remain 0)
        rd_addr = 5'd0;
        write_data = 32'h12345678;
        reg_write = 1;
        #10;
        
        // Verify x0 is still 0
        rs1_addr = 5'd0;
        reg_write = 0;
        #10;
        if (rs1_data !== 32'b0)
            $display("Test 5 failed: x0 should be hardwired to zero");
        else
            $display("Test 5 passed: x0 is hardwired to zero");
        
        // End simulation
        #10;
        $finish;
    end
    
    // Monitor changes
    initial begin
        $monitor("Time=%0t reset=%b rs1_addr=%d rs2_addr=%d rd_addr=%d write_data=%h reg_write=%b rs1_data=%h rs2_data=%h", 
                $time, reset, rs1_addr, rs2_addr, rd_addr, write_data, reg_write, rs1_data, rs2_data);
    end
endmodule

register_file_test.vcd
$date
	Tue Apr 29 02:19:34 2025
$end
$version
	Icarus Verilog
$end
$timescale
	1ps
$end
$scope module register_file_tb $end
$var wire 32 ! rs2_data [31:0] $end
$var wire 32 " rs1_data [31:0] $end
$var reg 1 # clk $end
$var reg 5 $ rd_addr [4:0] $end
$var reg 1 % reg_write $end
$var reg 1 & reset $end
$var reg 5 ' rs1_addr [4:0] $end
$var reg 5 ( rs2_addr [4:0] $end
$var reg 32 ) write_data [31:0] $end
$scope module uut $end
$var wire 1 # clk $end
$var wire 5 * rd_addr [4:0] $end
$var wire 1 % reg_write $end
$var wire 1 & reset $end
$var wire 5 + rs1_addr [4:0] $end
$var wire 5 , rs2_addr [4:0] $end
$var wire 32 - write_data [31:0] $end
$var wire 32 . rs2_data [31:0] $end
$var wire 32 / rs1_data [31:0] $end
$var integer 32 0 i [31:0] $end
$upscope $end
$upscope $end
$enddefinitions $end
$comment Show the parameter values. $end
$dumpall
$end
#0
$dumpvars
b100000 0
b0 /
b0 .
b0 -
b0 ,
b0 +
b0 *
b0 )
b0 (
b0 '
1&
0%
b0 $
0#
b0 "
b0 !
$end
#5000
b100000 0
1#
#10000
0#
#15000
b100000 0
1#
#20000
0#
1%
b10101011110011010001001000110100 )
b10101011110011010001001000110100 -
b1 $
b1 *
0&
#25000
1#
#30000
b10101011110011010001001000110100 "
b10101011110011010001001000110100 /
0#
0%
b1 '
b1 +
#35000
1#
#40000
0#
1%
b10000111011001010100001100100001 )
b10000111011001010100001100100001 -
b10 $
b10 *
#45000
1#
#50000
b10000111011001010100001100100001 !
b10000111011001010100001100100001 .
0#
0%
b10 (
b10 ,
#55000
1#
#60000
0#
1%
b10010001101000101011001111000 )
b10010001101000101011001111000 -
b0 $
b0 *
#65000
1#
#70000
b0 "
b0 /
0#
0%
b0 '
b0 +
